cerebrax/__init__.py
cerebrax/example.py
cerebrax-0.0.2.dist-info/licenses/LICENSE
cerebrax-0.0.2.dist-info/METADATA
cerebrax-0.0.2.dist-info/WHEEL
cerebrax-0.0.2.dist-info/entry_points.txt
cerebrax-0.0.2.dist-info/top_level.txt
cerebrax-0.0.2.dist-info/RECORD
