Metadata-Version: 2.4
Name: CerebraX
Version: 0.0.2
Summary: 名称预留：该项目 (CerebraX) 正在积极开发中。这是一个占位包，用于预留PyPI名称。
Author-email: CoolBlue-ww <3520352176@qq.com>
License: MIT
Project-URL: Homepage, https://github.com/CoolBlue-ww/CerebraX
Project-URL: Repository, https://github.com/CoolBlue-ww/CerebraX.git
Classifier: Development Status :: 2 - Pre-Alpha
Classifier: Intended Audience :: Developers
Classifier: License :: OSI Approved :: MIT License
Classifier: Programming Language :: Python :: 3
Classifier: Programming Language :: Python :: 3.8
Classifier: Programming Language :: Python :: 3.9
Classifier: Programming Language :: Python :: 3.10
Classifier: Programming Language :: Python :: 3.11
Requires-Python: >=3.8
License-File: LICENSE
Dynamic: license-file
